jiraclikit/__init__.py
jiraclikit/jc.py
jiraclikit-1.0.0.dist-info/METADATA
jiraclikit-1.0.0.dist-info/WHEEL
jiraclikit-1.0.0.dist-info/entry_points.txt
jiraclikit-1.0.0.dist-info/top_level.txt
jiraclikit-1.0.0.dist-info/RECORD
