Metadata-Version: 2.1
Name: jiraclikit
Version: 1.0.0
Summary: Kit (as in baby bunny) for Jira CLI.
Home-page: https://gitlab.com/q-os/security
Author: hashtagcyber
Author-email: domko@rabbit.tech
Requires-Python: >=3.12
Requires-Dist: requests
Requires-Dist: python-dotenv
